papyri_lab/__init__.py
papyri_lab/_version.py
papyri_lab/handlers.py
papyri_lab/tests/__init__.py
papyri_lab/tests/test_handlers.py
papyri_lab-0.0.1.data/data/etc/jupyter/jupyter_server_config.d/papyri_lab.json
papyri_lab-0.0.1.data/data/share/jupyter/labextensions/papyri-lab/build_log.json
papyri_lab-0.0.1.data/data/share/jupyter/labextensions/papyri-lab/package.json
papyri_lab-0.0.1.data/data/share/jupyter/labextensions/papyri-lab/schemas/papyri-lab/package.json.orig
papyri_lab-0.0.1.data/data/share/jupyter/labextensions/papyri-lab/schemas/papyri-lab/plugin.json
papyri_lab-0.0.1.data/data/share/jupyter/labextensions/papyri-lab/static/lib_index_js.454e946da84f62827b00.js
papyri_lab-0.0.1.data/data/share/jupyter/labextensions/papyri-lab/static/lib_index_js.454e946da84f62827b00.js.map
papyri_lab-0.0.1.data/data/share/jupyter/labextensions/papyri-lab/static/react-syntax-highlighter_languages_highlight_abnf.c75ea3a3197827dba6de.js
papyri_lab-0.0.1.data/data/share/jupyter/labextensions/papyri-lab/static/react-syntax-highlighter_languages_highlight_abnf.c75ea3a3197827dba6de.js.map
papyri_lab-0.0.1.data/data/share/jupyter/labextensions/papyri-lab/static/react-syntax-highlighter_languages_highlight_accesslog.79ae5c1f1662db990aec.js
papyri_lab-0.0.1.data/data/share/jupyter/labextensions/papyri-lab/static/react-syntax-highlighter_languages_highlight_accesslog.79ae5c1f1662db990aec.js.map
papyri_lab-0.0.1.data/data/share/jupyter/labextensions/papyri-lab/static/react-syntax-highlighter_languages_highlight_actionscript.d88c82655beec0c55580.js
papyri_lab-0.0.1.data/data/share/jupyter/labextensions/papyri-lab/static/react-syntax-highlighter_languages_highlight_actionscript.d88c82655beec0c55580.js.map
papyri_lab-0.0.1.data/data/share/jupyter/labextensions/papyri-lab/static/react-syntax-highlighter_languages_highlight_ada.0f21e543e389fab2eb74.js
papyri_lab-0.0.1.dist-info/METADATA
papyri_lab-0.0.1.dist-info/WHEEL
papyri_lab-0.0.1.dist-info/licenses/LICENSE
papyri_lab-0.0.1.dist-info/RECORD
